jupyterlab_midnightsea_theme/__init__.py
jupyterlab_midnightsea_theme/_version.py
jupyterlab_midnightsea_theme-0.1.5.data/data/share/jupyter/labextensions/jupyterlab_midnightsea_theme/package.json
jupyterlab_midnightsea_theme-0.1.5.data/data/share/jupyter/labextensions/jupyterlab_midnightsea_theme/static/568.b682367067f52b705021.js
jupyterlab_midnightsea_theme-0.1.5.data/data/share/jupyter/labextensions/jupyterlab_midnightsea_theme/static/remoteEntry.fd8d0ec9eba6fa861660.js
jupyterlab_midnightsea_theme-0.1.5.data/data/share/jupyter/labextensions/jupyterlab_midnightsea_theme/static/style.js
jupyterlab_midnightsea_theme-0.1.5.data/data/share/jupyter/labextensions/jupyterlab_midnightsea_theme/static/third-party-licenses.json
jupyterlab_midnightsea_theme-0.1.5.data/data/share/jupyter/labextensions/jupyterlab_midnightsea_theme/themes/jupyterlab_midnightsea_theme/index.css
jupyterlab_midnightsea_theme-0.1.5.data/data/share/jupyter/labextensions/jupyterlab_midnightsea_theme/themes/jupyterlab_midnightsea_theme/index.js
jupyterlab_midnightsea_theme-0.1.5.data/data/share/jupyter/labextensions/jupyterlab_midnightsea_theme/install.json
jupyterlab_midnightsea_theme-0.1.5.dist-info/METADATA
jupyterlab_midnightsea_theme-0.1.5.dist-info/WHEEL
jupyterlab_midnightsea_theme-0.1.5.dist-info/licenses/LICENSE
jupyterlab_midnightsea_theme-0.1.5.dist-info/licenses/LICENSE.txt
jupyterlab_midnightsea_theme-0.1.5.dist-info/RECORD
