Metadata-Version: 2.1
Name: jupyterlab_midnightsea_theme
Version: 0.1.5
Summary: A dark blue and purple JupyterLab theme extension.
Project-URL: Homepage, https://github.com/eduardotlc/jupyterlab_midnightsea_theme
Project-URL: Bug Tracker, https://github.com/eduardotlc/jupyterlab_midnightsea_theme/issues
Project-URL: Repository, https://github.com/eduardotlc/jupyterlab_midnightsea_theme.git
Author-email: Eduardo Campos <eduardotcampos@usp.br>
License: BSD 3-Clause License
License-File: LICENSE
License-File: LICENSE.txt
Classifier: Framework :: Jupyter
Classifier: Framework :: Jupyter :: JupyterLab
Classifier: Framework :: Jupyter :: JupyterLab :: 4
Classifier: Framework :: Jupyter :: JupyterLab :: Extensions
Classifier: Framework :: Jupyter :: JupyterLab :: Extensions :: Prebuilt
Classifier: License :: OSI Approved :: BSD License
Classifier: Programming Language :: Python
Classifier: Programming Language :: Python :: 3
Classifier: Programming Language :: Python :: 3.8
Classifier: Programming Language :: Python :: 3.9
Classifier: Programming Language :: Python :: 3.10
Classifier: Programming Language :: Python :: 3.11
Requires-Python: >=3.8
